versioner
tests
