Metadata-Version: 1.1
Name: versioner
Version: 0.0.7
Summary: A very basic command-line tool and library to keep track of the version of your project.
Home-page: http://josetomastocino.com
Author: José Tomás Tocino
Author-email: josetomas.tocino@gmail.com
License: GPLv2
Keywords: version versioning tool revision mayor minor
Platform: UNKNOWN
Classifier: Development Status :: 4 - Beta
Classifier: Environment :: Console
Classifier: Topic :: Utilities
Classifier: License :: OSI Approved :: GNU General Public License v2 (GPLv2)
Classifier: Programming Language :: Python
Classifier: Programming Language :: Python :: 2.7
